[
  {
    "id": "2a5de639b371c776ad804f652aabfa9b",
    "author": "offcourse",
    "title": "Align The Misaligned",
    "contentType": "course",
    "status": "draft",
    "checksum": "dd5ac0d7b37a244e895afcf3a8edda46"
  },
  {
    "id": "2af86ab4b101eec9b4126c6d5c1b9032",
    "author": "offcourse",
    "title": "Groom Your Ecosystem",
    "contentType": "course",
    "status": "draft",
    "checksum": "4b60a4026f5e3c6a215706d380f452d3",
    "habitat": "Across Space And Time"
  },
  {
    "id": "08073063de54f4aa2004bf7d0244aec0",
    "author": "offcourse",
    "title": "Keep The Web Weird",
    "contentType": "course",
    "status": "draft",
    "checksum": "f73a0dad773adccb86ce02345b460404",
    "habitat": "Align The Misaligned"
  },
  {
    "id": "325ac3289cb552a368dc65842cc2e9d9",
    "author": "offcourse",
    "title": "Practice Innovation",
    "contentType": "course",
    "status": "draft",
    "checksum": "42aea999e074e55044429b9e27c8c423"
  },
  {
    "id": "139bb1cdd4d42e26153699cee087b4c6",
    "author": "offcourse",
    "title": "Scale Effectively",
    "contentType": "course",
    "status": "published",
    "checksum": "1ea222b0e1f4fe474fed8275cb001150",
    "publicationData": {
      "createdAt": "2024-09-10T07:55:06.610Z",
      "updatedAt": "2024-09-10T07:55:06.610Z",
      "publishedAt": "2024-09-10T07:55:06.610Z"
    }
  },
  {
    "id": "09967adb4fa9242905164360276a69c3",
    "author": "offcourse",
    "title": "Offcourse - Share Knowledge",
    "contentType": "landing_page",
    "status": "published",
    "checksum": "e8e5e8bec9fc71e0963c3072e00cb4fd",
    "publicationData": {
      "createdAt": "2024-09-02T07:13:28.085Z",
      "updatedAt": "2024-09-02T07:13:28.085Z",
      "publishedAt": "2024-09-02T07:13:28.085Z"
    }
  },
  {
    "id": "ab2d83f1eb6532ec613531e32d4f1a12",
    "author": "offcourse",
    "title": "offcourse",
    "contentType": "profile",
    "status": "published",
    "checksum": "f65a4a50ad6cf1db291ab61694c40c92",
    "publicationData": {
      "createdAt": "2024-08-27T16:51:13.921Z",
      "updatedAt": "2024-08-27T16:51:13.921Z",
      "publishedAt": "2024-08-27T16:51:13.921Z"
    }
  }
]